pinterest_downloader/__init__.py
pinterest_downloader/downloader.py
pinterest_downloader-2.0.5.dist-info/METADATA
pinterest_downloader-2.0.5.dist-info/WHEEL
pinterest_downloader-2.0.5.dist-info/top_level.txt
pinterest_downloader-2.0.5.dist-info/RECORD
