Metadata-Version: 2.2
Name: pinterest_downloader
Version: 2.0.5
Summary: A Pinterest media downloader
Home-page: https://github.com/x7007x/pinterest-downloader
Author: Ahmed Negm
Author-email: a7mednegm.x@gmail.com
Classifier: Programming Language :: Python :: 3
Classifier: License :: OSI Approved :: MIT License
Classifier: Operating System :: OS Independent
Requires-Python: >=3.7
Requires-Dist: aiohttp
Dynamic: author
Dynamic: author-email
Dynamic: classifier
Dynamic: description
Dynamic: description-content-type
Dynamic: home-page
Dynamic: requires-dist
Dynamic: requires-python
Dynamic: summary
